preprocessing_text_ben/__init__.py
preprocessing_text_ben/utils.py
tweetben-0.0.1.dist-info/METADATA
tweetben-0.0.1.dist-info/WHEEL
tweetben-0.0.1.dist-info/top_level.txt
tweetben-0.0.1.dist-info/RECORD
