Metadata-Version: 2.1
Name: tweetben
Version: 0.0.1
Summary: This is for text preprocessing
Author: Behdad Ehsani
Author-email: behdad.ehsani@hec.ca
License: UNKNOWN
Platform: UNKNOWN
Classifier: Programming Language :: Python :: 3
Classifier: License :: OSI Approved :: MIT License
Classifier: Operating System :: OS Independent
